brightnessUI/__init__.py
brightnessUI/main.py
brightnessUI/image/logo.png
brightnessUI/install/__init__.py
brightnessUI/install/brightness-ui.sh
brightnessUI/install/create_desktop.py
brightnessUI/install/install_brightness_ui.py
brightnessUI/ui/backlight_slider.py
brightnessUI/ui/backlight_slider.ui
brightnessUI/ui/main_window.py
brightnessUI/ui/main_window.ui
brightnessUI/ui/password.py
brightnessUI/ui/password.ui
brightnessUI/ui/py_cmd.sh
brightnessUI-1.2.dist-info/LICENSE
brightnessUI-1.2.dist-info/METADATA
brightnessUI-1.2.dist-info/WHEEL
brightnessUI-1.2.dist-info/entry_points.txt
brightnessUI-1.2.dist-info/top_level.txt
brightnessUI-1.2.dist-info/RECORD
