Metadata-Version: 2.1
Name: brightnessUI
Version: 1.2
Summary: A simple UI to change screen backlight for ubuntu
Home-page: https://gitee.com/shu-peixuan/brightnessUI.git
Author: Peixuan Shu
Author-email: shupeixuan@qq.com
License: BSD
Keywords: A simple UI to tune screen backlight for ubuntu
Platform: UNKNOWN
Classifier: Development Status :: 2 - Pre-Alpha
Classifier: License :: OSI Approved :: BSD License
Classifier: Topic :: System :: Hardware :: Hardware Drivers
Classifier: Programming Language :: Python :: 3
Requires-Dist: PyQt5
